tinyrml/__init__.py
tinyrml/syntax.py
tinyrml/tinyrml.py
tinyrml-0.4.0.dist-info/licenses/LICENSE
tinyrml-0.4.0.dist-info/METADATA
tinyrml-0.4.0.dist-info/WHEEL
tinyrml-0.4.0.dist-info/top_level.txt
tinyrml-0.4.0.dist-info/RECORD
