Metadata-Version: 2.4
Name: tinyrml
Version: 0.4.0
Summary: Implementation of a subset of R2RML and RML
Author-email: Ora Lassila <ora@somanyaircraft.com>
License-Expression: BSD-3-Clause
Project-URL: Homepage, https://gitlab.com/somanyaircraft/tinyrml
Classifier: Development Status :: 4 - Beta
Classifier: Programming Language :: Python :: 3
Classifier: Operating System :: OS Independent
Requires-Python: >=3.8
License-File: LICENSE
Dynamic: license-file
